{
  "id": "ai-code-reviewer-env",
  "name": "AI Code Reviewer Environment",
  "values": [
    {
      "key": "baseUrl",
      "value": "https://localhost:7001",
      "type": "default",
      "enabled": true
    },
    {
      "key": "host",
      "value": "localhost:7001",
      "type": "default",
      "enabled": true
    },
    {
      "key": "apiPath",
      "value": "/api",
      "type": "default",
      "enabled": true
    },
    {
      "key": "currentOwner",
      "value": "microsoft",
      "type": "default",
      "enabled": true
    },
    {
      "key": "currentRepo",
      "value": "vscode",
      "type": "default",
      "enabled": true
    },
    {
      "key": "prNumber",
      "value": "1",
      "type": "default",
      "enabled": true
    },
    {
      "key": "commitSha",
      "value": "",
      "type": "default",
      "enabled": true
    },
    {
      "key": "testOwner",
      "value": "octocat",
      "type": "default",
      "enabled": true
    },
    {
      "key": "testRepo",
      "value": "Hello-World",
      "type": "default",
      "enabled": true
    }
  ],
  "_postman_variable_scope": "environment"
}
